misskey/__init__.py
misskey/enum.py
misskey/exceptions.py
misskey/miauth.py
misskey/misskey.py
Misskey.py-4.1.0.dist-info/LICENSE
Misskey.py-4.1.0.dist-info/METADATA
Misskey.py-4.1.0.dist-info/WHEEL
Misskey.py-4.1.0.dist-info/top_level.txt
Misskey.py-4.1.0.dist-info/RECORD
