Metadata-Version: 2.1
Name: Misskey.py
Version: 4.1.0
Summary: The misskey library for Python. misskey is made by syuilo.
Home-page: https://github.com/YuzuRyo61/Misskey.py
Author: YuzuRyo61
License: MIT
Keywords: misskey,API,library,syuilo,SNS,Social Networking Service
Platform: UNKNOWN
Classifier: License :: OSI Approved :: MIT License
Classifier: Development Status :: 5 - Production/Stable
Classifier: Natural Language :: English
Classifier: Natural Language :: Japanese
Classifier: Programming Language :: Python :: 3 :: Only
Classifier: Programming Language :: Python :: 3
Classifier: Programming Language :: Python :: 3.7
Classifier: Programming Language :: Python :: 3.8
Classifier: Programming Language :: Python :: 3.9
Classifier: Programming Language :: Python :: 3.10
Classifier: Topic :: Software Development :: Libraries :: Python Modules
Classifier: Topic :: Software Development :: Libraries
Classifier: Topic :: Internet :: WWW/HTTP
Classifier: Topic :: Internet
Classifier: Topic :: Communications
License-File: LICENSE
Requires-Dist: requests
